{"cameraMode":{"drawMode":0,"name":"Shaded","section":"Shading Mode"},"sceneLighting":false,"audioPlay":false,"sceneViewState":{"m_AlwaysRefresh":false,"showFog":true,"showSkybox":true,"showFlares":true,"showImageEffects":true,"showParticleSystems":true,"showVisualEffectGraphs":true,"m_FxEnabled":true},"in2DMode":false,"pivot":{"x":-29.44002914428711,"y":-161.01319885253907,"z":-11.515396118164063},"rotation":{"x":-0.011050053872168064,"y":0.8178441524505615,"z":-0.5751408338546753,"w":-0.01570451259613037},"size":188.4994659423828,"orthographic":false}